pyconform/__init__.py
pyconform/climIO.py
pyconform/dataflow.py
pyconform/datasets.py
pyconform/flownodes.py
pyconform/functions.py
pyconform/indexing.py
pyconform/mapdates.py
pyconform/miptableparser.py
pyconform/parsetab.py
pyconform/parsing.py
pyconform/physarray.py
pyconform/cli/__init__.py
pyconform/cli/iconform.py
pyconform/cli/vardeps.py
pyconform/cli/xconform.py
pyconform/modules/CLM_landunit_to_CMIP6_Lut.py
pyconform/modules/CLM_pft_to_CMIP6_vegtype.py
pyconform/modules/__init__.py
pyconform/modules/atm_funcs.py
pyconform/modules/commonfunctions.py
pyconform/modules/dynvarmipdiags.py
pyconform/modules/dynvarmipfunctions.py
pyconform/modules/idl.py
pyconform/modules/pnglfunctions.py
tests/modules/__init__.py
tests/modules/dynvarmipdiagsTests.py
tests/modules/idlTests.py
PyConform-0.3.0.dist-info/LICENSE.rst
PyConform-0.3.0.dist-info/METADATA
PyConform-0.3.0.dist-info/WHEEL
PyConform-0.3.0.dist-info/entry_points.txt
PyConform-0.3.0.dist-info/top_level.txt
PyConform-0.3.0.dist-info/RECORD
