Metadata-Version: 2.1
Name: PyConform
Version: 0.3.0
Summary: Parallel Python NetCDF Dataset Standardization Tool
Home-page: https://github.com/NCAR/PyConform
Author: Kevin Paul
Author-email: kpaul@ucar.edu
License: UNKNOWN
Platform: UNKNOWN
Classifier: Programming Language :: Python :: 2.7
Classifier: Programming Language :: Python :: 3.6
Classifier: Programming Language :: Python :: 3.7
Classifier: Programming Language :: Python :: 3.8
Classifier: License :: OSI Approved :: Apache Software License
Classifier: Operating System :: OS Independent
Classifier: Topic :: Scientific/Engineering
Classifier: Topic :: Scientific/Engineering :: Atmospheric Science
Classifier: Topic :: Utilities
Requires-Python: >=2.7
Requires-Dist: asaptools
Requires-Dist: cf-units
Requires-Dist: netCDF4
Requires-Dist: numpy
Requires-Dist: ply
Requires-Dist: python-dateutil
